today/Pretty.py
today/Questionairre.py
today/__init__.py
today/__main__.py
today/cli.py
today/entries.py
yesterday/Pretty.py
yesterday/Questionairre.py
yesterday/Questionnaire.py
yesterday/__init__.py
yesterday/__main__.py
yesterday/cli.py
yesterday/entries.py
yesterday-1.0.1.dist-info/METADATA
yesterday-1.0.1.dist-info/WHEEL
yesterday-1.0.1.dist-info/entry_points.txt
yesterday-1.0.1.dist-info/top_level.txt
yesterday-1.0.1.dist-info/RECORD
